{"_id":"2754ec90-5461-11eb-8c0c-45b49edb66f8","name":"TerryVam","website":"https://moshavere-bartar.ir/forums/topic/scabioral-preis-scabioral-500mg-kaufen/","email":"d65dc3f6d682bb9e9fa473768b93947a","body":"<b><a href=http://fito-spray-spain.com/a/peen/aralen.html>Visit Secure Drugstore >> Click Here! << </a></b> \r\n \r\n \r\n<a href=http://fito-spray-spain.com/a/peen/chloroquine.html><img src=\"https://i.imgur.com/P8dh1bB.jpg\"></a> \r\n \r\n \r\n<b><a href=http://fito-spray-spain.com/a/peen/aralen.html>Visit Secure Drugstore >> Click Here! << </a></b> \r\n \r\n \r\n \r\n \r\n \r\n \r\n \r\n \r\n \r\n \r\n \r\n \r\n \r\n \r\n \r\nNeben der Entwicklung von CFS, die Patienten in der Regel bereits ein oder mehrere Gesundheitsthemen, dass sie mit streitenden und versuchen, mit Medikamenten aus ihren Gesundheitsdienstleister Kontrolle \r\nkaufen bitcoin kaufen medizin online https://olammacares.com/forums/topic/dapoxetin-ausland-kaufen/ Kaufen Online in Deutschland Heilbronn \r\nNaturlich sind diese Symptome haufig sind bei anderen Krankheiten wie Bluthochdruck, Mononukleose, und Grippe, sie in der Regel nichts, was die moderne Medizin und Tests in der Lage, aus dem Korper zu eliminieren sind \r\nEinige Dusche Filter sollen am Ende des Rohres angebracht werden, manchmal zwischen dem Rohr und der Duschkopf \r\nonline kaufen emmen apotheke rezeptfrei bestellen http://www.conspiracybase.com/forum/viewtopic.php?p=807794#807794 online kaufen Thurgau Osnabruck \r\n<li> Reizdarmsyndrom </ li> \r\n<a href=https://www.rede-do-territorio.pt/forum/viewtopic.php?pid=876981#p876981>coronavirus australien tod Behandlung von Rhinitis nt9w</a> Du musst vorsichtig sein, uber die Beratung, die Sie treffen, weil es manchmal fuhren kann Ihnen mit Hilfe von Formeln auf Ihrer Haut, sind nicht so gesund fur Sie, wie Sie vielleicht denken \r\nDas war vor dem Zeitalter der Kosmetik-Unternehmen, und als sie an die Macht den Weg, dass wir die Behandlung kam unsere Haut hat eine bestimmte Wendung zum Schlechteren \r\ngenerika günstig online kaufen apotheke in niederlande berlin https://olammacares.com/forums/forum/covid-19-and-mental-health/ online bestellen auf rechnung buy medizin für frauen auf rechnung bestellen generika generikum https://mashlimim.co.il/forums/topic/stromectol-stada-50-mg-rezeptfrei-generika-stromectol-online-apotheke/ Preis Darmstadt \r\ngünstig bestellen buy  online holland http://drghodosi.com/forums/topic/gute-online-apotheke-pregabalin/ rezeptfrei 100% Befriedigung Garantie! \r\nWenn dies passiert, gibt es eine gute Chance, dass Sie ein Leidender von CFS sind und Sie sollten diese Besorgnis zu bringen back up mit Ihrem Arzt \r\nVerbraucher neigen dazu, die Inhaltsstoffe weiter unten das Etikett zu ignorieren, und die durch Nichtbeachtung ihnen konnte man sein Verkurzung Ihres Lebens \r\nseriös kaufen Möhlin ausverkauf apotheke internet https://olammacares.com/forums/topic/ivermectin-zu-verkaufen-deutschland-kaufen-ivermectin-20-mg-generic-deutschlan/ 300 mcg preis schweiz einkauf  online apotheke generika kaufen auf rechnung mieten medizin https://mashlimim.co.il/forums/topic/rezept-fur-generisches-scabioral-scabioral-online-kaufen/ Online Ohne Rezept Kaufen Darmstadt \r\nkaufen rezeptfrei ubersenden  online https://mashlimim.co.il/forums/topic/scabioral-250-mg-kaufen-stromectol-generika-rezeptfrei-kaufen/ schweiz preis buy  online generika \r\nbeautiful-Haut-site \r\nNaturliche Inhaltsstoffe eher schlecht gehen ziemlich schnell, und so Ma?nahmen mussten ergriffen werden, um zu versichern, dass die Verbindungen in Kosmetika frisch geblieben \r\n300 mcg online bestellen köniz verkaufen tablette https://torah-idf.org.il/forums/topic/anwendung-ciprofloxacin/ bester preis ohne rezept kaufen uber internet! kaufen bitcoin kaufen https://mashlimim.co.il/forums/topic/wo-bestellen-ivermectin-houston-scabioral-online-bestellen-rezeptfrei/ Online Ohne Rezept Kaufen Duisburg \r\ngenerika medikament rezeptfrei bestellen rezeptfrei potenzmittel https://moshavere-bartar.ir/forums/forum/ЩѕШ±ШіШґ-Щ€-ЩѕШ§ШіШ®/ online kaufen wallis kaufen arznei tablette \r\n<a href=https://forum.compucoin.org/showthread.php?tid=631826&pid=1324633#pid1324633>Behandlung Zwinger Husten Medikamente zur Senkung des Hirndrucks fizj</a> Wenn dies geschieht wird der Korper nach links zu tragen und anfallig fur viele andere Krankheiten, die zu CFS und anderen Gesundheitsproblemen fuhren kann \r\n \r\nsjdhsjdhjs22","date":"2021-01-11T23:03:01.954Z"}