{"_id":"5a273740-46b0-11eb-9592-fb6f06bd417b","name":"RobertTwele","website":"https://mobile-casino.me/","email":"8c64cd79be2b44c3821a6987cfe24a2e","body":"Can you win cash on online casinos? \r\nYes, playing online casino games are real chanse as a service to Australian players. ... When online gambling for authentic paper money, it is vital to induce a entrust into your casino account. The best online casinos offer their players a sizeable choice of honourable banking options to accumulation and void their cash \r\nTry this  website \r\nhttps://mobile-casino.me/ - mobile-casino.me>>>","date":"2020-12-25T12:54:40.892Z"}