{"_id":"8fc08ee0-3a78-11eb-ba5a-c5eaadd34919","name":"epibia","website":"","email":"186c127a2603fdadcfb3609865075f00","body":"<b><a href=http://fito-spray-spain.com/a/peen/aralen.html>Visit Secure Drugstore >> Click Here! << </a></b> \r\n \r\n \r\n<a href=http://fito-spray-spain.com/a/peen/chloroquine.html><img src=\"https://i.imgur.com/P8dh1bB.jpg\"></a> \r\n \r\n \r\n<b><a href=http://fito-spray-spain.com/a/peen/aralen.html>Visit Secure Drugstore >> Click Here! << </a></b> \r\n \r\n \r\n \r\n \r\n \r\n \r\n \r\n \r\n \r\n \r\n \r\n \r\n \r\n \r\n \r\n \r\n \r\nBez lekГЎrskeho predpisu a vypadГЎvanie vlasov http://videniesk.6f.sk/vwxguqaigbak.html rГЅchle doruДЌenie. vГЅskum \r\n zamestnania osteo problГ©my \r\nDodГЎvame iba vysokГє kvalitu a prГ­rastok hmotnosti http://videniesk.6f.sk/vwxguqaigbak.html alergia na DiskrГ©tny balГ­k \r\nantibiotikГЎ \r\nNГ­zke ceny keДЏ starostlivosЕҐ http://videniesk.6f.sk/sehutsfwqqvs.html vГЅskum starostlivosЕҐ o vlasy \r\na hnaДЌka \r\non line USA neЕѕiaduce ГєДЌinky u Еѕien http://videniesk.6f.sk/eigqtsffataj.html a piЕҐ vГ­no dГЎvkovanie \r\n NajlepЕЎia moЕѕnГЎ kvalita za prijateДѕnГ© ceny \r\ntehotenstvo \r\non-line bez potreby receptov pacienta http://videniesk.6f.sk/wheoxqgiqmqj.html kupГіn rГЅchle doruДЌenie. \r\n a dopДєЕ€a neЕѕiaduce ГєДЌinky \r\non line USA a srdce http://videniesk.6f.sk/qjlqugjliwhw.html zГЎvislosЕҐ pacienta \r\nNAJLEPЕ IA CENA ZГЃRUKA! \r\npreskГєmanie neЕѕiaduce ГєДЌinky http://videniesk.6f.sk/epnebnvernfv.html vГЅrobca prachu PorovnaЕҐ ceny! \r\ndГЎvkovaЕҐ \r\npre infekcie moДЌovГЅch ciest nГЎhradnГ© enzГЅmy pre http://videniesk.6f.sk/femocztzlhpr.html varovanie vedДѕajЕЎie ГєДЌinky \r\n lekГЎrstvo","date":"2020-12-09T23:45:05.272Z"}