{"_id":"94bf6ab0-5ee0-11eb-b431-b1c504334b43","name":"Ceska_erype","website":"http://www.capitalbikepark.se/bok/go.php?url=https://czechorgy.club/","email":"4c53d1ef8ca7182cc9588c0a37efabc6","body":"She is so Sexy and Hot. I would start with her Hot Feet  You will be able to taste my fruits and lively body so that you would never forget how sweet it tastes   <a href=https://nl.xhamster4.com/exit.php?url=https://czxxxtube.me/>http://www.jatrader.ru/redirect?url=https://hotczech.me/ </a> No matter how much time you will give for her, you can be sure that she will use it fully  Silver, feel free to post and let us know... how you are doing. He may have some nice points, but there is a whole lot of things that he says and does that brings you down, and they aren't trivial.   <a href=http://mir-stekla96.ru/bitrix/rk.php?goto=https://fapercs.me/>http://www.sonce.net/redirect.php?url=https://xxxscr.me/ </a> She knows where to put arms, how to use her stunning body to make you burn in delight to have much more from her","date":"2021-01-25T07:40:22.952Z"}