{"_id":"e488b5a0-8fa2-11ea-ac66-b105df757730","name":"BusinessLoanFunded","website":"","email":"c6ac07f05699a44fa99f56d08b763ed2","body":"Faster and Simpler than the SBA, http://Business-Loan-Funded.info?url=carlbfrederick.com can get your business a loan for $2K-350,000 With low-credit and no collateral. \r\n \r\nUse our 1 minute form to See exactly how much you can get, No-Cost: \r\n \r\nhttp://Business-Loan-Funded.info?url=carlbfrederick.com \r\n \r\nIf you've been in business for at least a year you are already pre-qualified. Our Quick service means funding can be finished within 48 hours. Terms are specific for each business so I suggest applying to find out exactly how much you can get. \r\n \r\nThis is a free service from a qualified lender and the approval will be based on the annual revenue of your business. Funds are also Non-Restrictive, allowing you to use the full amount in any way including bills, taxes, hiring, marketing, expansion, or Absolutely Any Other expense. \r\n \r\nThere are limited SBA and private funds available so please apply now if interested, \r\n \r\nClick Here: http://Business-Loan-Funded.info?url=carlbfrederick.com \r\n \r\nHave a great day, \r\nThe Business Loan Funded Team \r\n \r\nremove here - http://business-loan-funded.info/r.php?url=carlbfrederick.com&id=102","date":"2020-05-06T14:07:17.597Z"}