{"_id":"f5dcc990-61e3-11eb-93ca-2b465beb6e71","name":"ShishkiVaRdy","website":"https://shishki.tk/","email":"5daf2168384ec86b028b4ab74efbc80b","body":"Гашишем принято называть наркотическое вещество, которое изготавливается из растения конопля, оно оказывает психотропное воздействие на человеческое сознание. Среди зависимых наркотик часто называют шайбой. Крайне сложно вычислить точно, употребляет ли человек гашиш. Однако стоит учесть, что некоторые поведенческие изменения выдадут наркомана. Пока еще точно неизвестно, по какому признаку изготавливается шайба. Но ясно то, что <a href=https://shishki.tk>гашиш москвы</a> среди компонентов гашиша есть конопля, спрессованная определенным методом. Именно смола растения дает психоактивное воздействие. «Брикеты» наркотического вещества могут быть изготовлены различного размера, веса. \r\n \r\nВ настоящее время найти гашишное масло можно только на черном рынке. Как и любое другое наркотическое вещество, гашиш при длительном употреблении способен оказывать губительное действие на организм человека. В состав этого наркотического препарата входит около 400 различных химических соединений, из которых более 60 составляют каннабиоиды. После попадания в кровь все эти вещества разносятся по организму и <a href=https://shishki.tk>Закладки Каннабис Балашиха</a> разным органам и системам человека. Чем выше концентрация вредных веществ в наркотике, тем сильнее будет его действие. \r\n \r\nПосле первого употребления гашиша человек может не почувствовать никакого эффекта, но  \r\n<a href=https://shishki.tk/pink-og.html>Купить Бошки Егорьевск</a> на этом не останавливается и учится правильно делать затяжки. На начальном этапе развития наркотической зависимости у человека возникают нарушения восприятия времени и пространства, ощущение страха, паники и тревоги. Наркозависимый выглядит несколько заторможенным и апатичным, у него повышается аппетит.","date":"2021-01-29T03:42:07.924Z"}