{"_id":"ff9e5140-2631-11ea-b447-d15e5a4fc84f","name":"Scottheess","website":"https://essaywritingservicecanada153.blogspot.com","email":"59977748fedde6465d72a08ad8ea3e94","body":"British Assignments Support has group of main essay writers who include the most efficient essay crafting company in United kingdom at reasonably priced price ranges, get price reduction on your own initial get.\r\n \r\nhttps://whattoputunderskillsonaresume.blogspot.com\r\nhttps://resumedimensions163.blogspot.com\r\nhttps://howwewriteanessay912.blogspot.com\r\nhttps://howtowriteskillsonresume.blogspot.com\r\nhttps://hairstylistresume.blogspot.com\r\nhttps://digitalmarketingresume788.blogspot.com\r\nhttps://howtowriteaanalyticalessay440.blogspot.com\r\nhttps://journalismresume.blogspot.com\r\nhttps://collegeessaywriters634.blogspot.com\r\nhttps://engineeringresumeexamples.blogspot.com\r\nhttps://resumedimensions.blogspot.com\r\nhttps://buyessaysonline858.blogspot.com\r\nhttps://interestsonaresume.blogspot.com\r\nhttps://babysitterresume153.blogspot.com\r\nhttps://partsofaresume.blogspot.com\r\nhttps://executiveresumesamples737.blogspot.com\r\nhttps://goodfontforresume.blogspot.com\r\nhttps://bestresumewritingservices137.blogspot.com\r\nhttps://objectivesinaresume.blogspot.com\r\nhttps://howtowriteasatireessay641.blogspot.com\r\nhttps://resumeskillwords.blogspot.com\r\nhttps://resumedatabase808.blogspot.com\r\nhttps://collegeenglishessays510.blogspot.com\r\nhttps://itresumeexample.blogspot.com\r\nhttps://sampleresumeforteachers.blogspot.com\r\nhttps://helpwritingessaysforcollege249.blogspot.com\r\nhttps://insidesalesresume707.blogspot.com\r\nhttps://machinelearningengineerresume306.blogspot.com\r\nhttps://customerserviceresume157.blogspot.com\r\nhttps://simpleresumeformatinword.blogspot.com\r\nhttps://writedescriptiveessay881.blogspot.com\r\nhttps://easycertificationstoaddtoyourresume.blogspot.com\r\nhttps://merchandiserresume.blogspot.com\r\nhttps://myperfectresumelogin750.blogspot.com\r\nhttps://howtoendaresume.blogspot.com\r\nhttps://howtomakeanactingresume575.blogspot.com\r\nhttps://resumefornoexperience.blogspot.com\r\nhttps://resumedef959.blogspot.com\r\nhttps://websiteresume104.blogspot.com\r\nhttps://bestfontsizeforresume2017.blogspot.com\r\nhttps://stevebannonresume.blogspot.com\r\nhttps://howtoshowapromotiononaresume181.blogspot.com\r\nhttps://managementresume.blogspot.com\r\nhttps://goodresumeexamples.blogspot.com\r\nhttps://pythonprojectsforresume379.blogspot.com\r\nhttps://technicaltheatreresume.blogspot.com\r\nhttps://needhelpwritingaessay7.blogspot.com\r\nhttps://resumeforserver.blogspot.com\r\nhttps://manufacturingresumeexamples181.blogspot.com\r\nhttps://helpwithcollegeessaywriting31.blogspot.com\r\nhttps://objectiveforresumesamples971.blogspot.com\r\nhttps://stevebannonresume738.blogspot.com\r\nhttps://howtowriteamlaessay336.blogspot.com\r\nhttps://tipsforwritingaresume768.blogspot.com\r\nhttps://howtomakeacoverletterforaresume.blogspot.com\r\nhttps://collegeessaytutors639.blogspot.com\r\nhttps://professionalessaywritinghelp604.blogspot.com\r\nhttps://resumestatementofpurpose.blogspot.com\r\nhttps://examplehighschoolresume.blogspot.com\r\nhttps://resumeprofilesamples.blogspot.com\r\nhttps://createaresume152.blogspot.com\r\nhttps://resumeforbanktellers164.blogspot.com\r\nhttps://graduateschooladmissionsessay806.blogspot.com\r\nhttps://senioraccountantresume.blogspot.com\r\nhttps://wheretoaddresumeonlinkedin650.blogspot.com\r\nhttps://2018resume365.blogspot.com\r\nhttps://pythonprojectsforresume936.blogspot.com\r\nhttps://functionalresumetemplate2018.blogspot.com\r\nhttps://courseworkresume.blogspot.com\r\nhttps://howtoputtogetheraresume70.blogspot.com\r\nhttps://howtoimproveyouressaywriting331.blogspot.com\r\nhttps://resumetemplatesfree939.blogspot.com\r\nhttps://communicationresumeexamples5.blogspot.com\r\nhttps://webdeveloperresumeexamples.blogspot.com\r\nhttps://linkediniconforresume.blogspot.com\r\nhttps://dietaryaideresume.blogspot.com\r\nhttps://tsaleapresume138.blogspot.com\r\nhttps://myperfectresume439.blogspot.com\r\nhttps://essayswriter211.blogspot.com\r\nhttps://emailresume516.blogspot.com\r\nhttps://writingessayonline3.blogspot.com\r\nhttps://itinternresume.blogspot.com\r\nhttps://leadershipresumeexamples406.blogspot.com\r\nhttps://sampleengineeringresume677.blogspot.com\r\nhttps://ejemploderesume497.blogspot.com\r\nhttps://designwritingpaper102.blogspot.com\r\nhttps://softskillsonresume.blogspot.com\r\nhttps://bldresumecharge.blogspot.com\r\nhttps://resumeforgraphicdesigner.blogspot.com\r\nhttps://howtowritearesumeforcollege568.blogspot.com\r\nhttps://networkengineerresume662.blogspot.com\r\nhttps://shadowingonresume515.blogspot.com\r\nhttps://writingessaysforuniversity254.blogspot.com\r\nhttps://howtowritea250wordessay187.blogspot.com\r\nhttps://howtolisteducationonaresume.blogspot.com\r\nhttps://howtoorganizearesume554.blogspot.com\r\nhttps://professionalessaywritinghelp277.blogspot.com\r\nhttps://summariesforaresume.blogspot.com\r\nhttps://excellentresume60.blogspot.com\r\nhttps://writingresearchpapers954.blogspot.com","date":"2019-12-24T09:44:37.464Z"}